Ejercicios_Unidad_2/actividad_3/actividad_3.v
// contador
`timescale 1ns/1ps

module actividad_3 (
  input  wire        clk,
  input  wire        rst,
  input  wire        en,
  output reg  [3:0]  count,
  output reg         tc
);

always @(posedge clk) begin

    tc <= 1'b0;   // por defecto no hay terminal count

    if (rst) begin
        count <= 4'd0;
    end
    else if (en) begin

        if (count < 4'd9) begin
            count <= count + 4'd1;
        end
        else begin
            count <= 4'd0;
            tc <= 1'b1;
        end

    end

end

endmodule

Ejercicios_Unidad_2/actividad_3/tb_actividad_3.v
`timescale 1ns/1ps

module tb_actividad_3;

    reg clk;
    reg rst;
    reg en;

    wire [3:0] count;
    wire tc;


    // Golden model
    reg [3:0] gold_count;
    reg gold_tc;


    integer i;
    integer rollover_count;


    // Instancia del DUT
    actividad_3 dut (
        .clk(clk),
        .rst(rst),
        .en(en),
        .count(count),
        .tc(tc)
    );


    always #5 clk = ~clk;


    initial begin
        $dumpfile("tb_actividad_3.vcd");
        $dumpvars(0, tb_actividad_3);
    end



    // Golden model muy parecido a la actividad porque se deben comparar

    always @(posedge clk) begin

        if (rst) begin

            gold_count <= 4'd0;
            gold_tc <= 1'b0;

        end

        else if (en) begin

            if (gold_count == 4'd9) begin

                gold_count <= 4'd0;
                gold_tc <= 1'b1;

            end

            else begin

                gold_count <= gold_count + 4'd1;
                gold_tc <= 1'b0;

            end

        end

        else begin

            gold_tc <= 1'b0;

        end

    end

        // Auto-check
    always @(posedge clk) begin
        #1;

        if (count !== gold_count) begin
            $display("ERROR: count=%d esperado=%d", count, gold_count);
            $finish;
        end

        if (tc !== gold_tc) begin
            $display("ERROR: tc=%d esperado=%d", tc, gold_tc);
            $finish;
        end
    end

    // --------------------------------
    // Test principal
    // --------------------------------

    initial begin

        clk = 0;
        rst = 1;
        en  = 0;

        gold_count = 4'd0;
        gold_tc = 1'b0;

        rollover_count = 0;



        @(posedge clk);
        #1;

        rst = 0;
        en = 1;



        // Prueba de reset después de 5 ciclos
        $display("Prueba de RESET sincrono");


        repeat(5) begin
            @(posedge clk);
            #1;
        end


        $display("Valor antes del reset: count=%d", count);



        // Activar reset síncrono
        rst = 1;


        @(posedge clk);
        #1;

        $display("Valor despues del reset: count=%d", count);



        // Quitar reset

        rst = 0;


        // Prueba de 100 ciclos

        $display("Prueba de 100 ciclos");


        rollover_count = 0;


        for (i = 0; i < 100; i = i + 1) begin

            @(posedge clk);
            #1;


            if (tc)
                rollover_count = rollover_count + 1;

        end



        $display("Rollovers detectados: %d",
                 rollover_count);

        $finish;


    end


endmodule

Ejercicios_Unidad_2/actividad_3/tb_actividad_3.vcd
$date
	Wed Aug  5 17:17:51 2026
$end
$version
	Icarus Verilog
$end
$timescale
	1ps
$end
$scope module tb_actividad_3 $end
$var wire 1 ! tc $end
$var wire 4 " count [3:0] $end
$var reg 1 # clk $end
$var reg 1 $ en $end
$var reg 4 % gold_count [3:0] $end
$var reg 1 & gold_tc $end
$var reg 1 ' rst $end
$var integer 32 ( i [31:0] $end
$var integer 32 ) rollover_count [31:0] $end
$scope module dut $end
$var wire 1 # clk $end
$var wire 1 $ en $end
$var wire 1 ' rst $end
$var reg 4 * count [3:0] $end
$var reg 1 ! tc $end
$upscope $end
$upscope $end
$enddefinitions $end
#0
$dumpvars
bx *
b0 )
bx (
1'
0&
b0 %
0$
0#
bx "
x!
$end
#5000
b0 "
b0 *
0!
1#
#6000
1$
0'
#10000
0#
#15000
b1 %
b1 "
b1 *
1#
#20000
0#
#25000
b10 "
b10 *
b10 %
1#
#30000
0#
#35000
b11 %
b11 "
b11 *
1#
#40000
0#
#45000
b100 "
b100 *
b100 %
1#
#50000
0#
#55000
b101 %
b101 "
b101 *
1#
#56000
1'
#60000
0#
#65000
b0 "
b0 *
b0 %
1#
#66000
b0 (
0'
#70000
0#
#75000
b1 %
b1 "
b1 *
1#
#76000
b1 (
#80000
0#
#85000
b10 "
b10 *
b10 %
1#
#86000
b10 (
#90000
0#
#95000
b11 %
b11 "
b11 *
1#
#96000
b11 (
#100000
0#
#105000
b100 "
b100 *
b100 %
1#
#106000
b100 (
#110000
0#
#115000
b101 %
b101 "
b101 *
1#
#116000
b101 (
#120000
0#
#125000
b110 "
b110 *
b110 %
1#
#126000
b110 (
#130000
0#
#135000
b111 %
b111 "
b111 *
1#
#136000
b111 (
#140000
0#
#145000
b1000 "
b1000 *
b1000 %
1#
#146000
b1000 (
#150000
0#
#155000
b1001 %
b1001 "
b1001 *
1#
#156000
b1001 (
#160000
0#
#165000
1!
b0 "
b0 *
1&
b0 %
1#
#166000
b1010 (
b1 )
#170000
0#
#175000
0&
b1 %
b1 "
b1 *
0!
1#
#176000
b1011 (
#180000
0#
#185000
b10 "
b10 *
b10 %
1#
#186000
b1100 (
#190000
0#
#195000
b11 %
b11 "
b11 *
1#
#196000
b1101 (
#200000
0#
#205000
b100 "
b100 *
b100 %
1#
#206000
b1110 (
#210000
0#
#215000
b101 %
b101 "
b101 *
1#
#216000
b1111 (
#220000
0#
#225000
b110 "
b110 *
b110 %
1#
#226000
b10000 (
#230000
0#
#235000
b111 %
b111 "
b111 *
1#
#236000
b10001 (
#240000
0#
#245000
b1000 "
b1000 *
b1000 %
1#
#246000
b10010 (
#250000
0#
#255000
b1001 %
b1001 "
b1001 *
1#
#256000
b10011 (
#260000
0#
#265000
1!
b0 "
b0 *
1&
b0 %
1#
#266000
b10100 (
b10 )
#270000
0#
#275000
0&
b1 %
b1 "
b1 *
0!
1#
#276000
b10101 (
#280000
0#
#285000
b10 "
b10 *
b10 %
1#
#286000
b10110 (
#290000
0#
#295000
b11 %
b11 "
b11 *
1#
#296000
b10111 (
#300000
0#
#305000
b100 "
b100 *
b100 %
1#
#306000
b11000 (
#310000
0#
#315000
b101 %
b101 "
b101 *
1#
#316000
b11001 (
#320000
0#
#325000
b110 "
b110 *
b110 %
1#
#326000
b11010 (
#330000
0#
#335000
b111 %
b111 "
b111 *
1#
#336000
b11011 (
#340000
0#
#345000
b1000 "
b1000 *
b1000 %
1#
#346000
b11100 (
#350000
0#
#355000
b1001 %
b1001 "
b1001 *
1#
#356000
b11101 (
#360000
0#
#365000
1!
b0 "
b0 *
1&
b0 %
1#
#366000
b11110 (
b11 )
#370000
0#
#375000
0&
b1 %
b1 "
b1 *
0!
1#
#376000
b11111 (
#380000
0#
#385000
b10 "
b10 *
b10 %
1#
#386000
b100000 (
#390000
0#
#395000
b11 %
b11 "
b11 *
1#
#396000
b100001 (
#400000
0#
#405000
b100 "
b100 *
b100 %
1#
#406000
b100010 (
#410000
0#
#415000
b101 %
b101 "
b101 *
1#
#416000
b100011 (
#420000
0#
#425000
b110 "
b110 *
b110 %
1#
#426000
b100100 (
#430000
0#
#435000
b111 %
b111 "
b111 *
1#
#436000
b100101 (
#440000
0#
#445000
b1000 "
b1000 *
b1000 %
1#
#446000
b100110 (
#450000
0#
#455000
b1001 %
b1001 "
b1001 *
1#
#456000
b100111 (
#460000
0#
#465000
1!
b0 "
b0 *
1&
b0 %
1#
#466000
b101000 (
b100 )
#470000
0#
#475000
0&
b1 %
b1 "
b1 *
0!
1#
#476000
b101001 (
#480000
0#
#485000
b10 "
b10 *
b10 %
1#
#486000
b101010 (
#490000
0#
#495000
b11 %
b11 "
b11 *
1#
#496000
b101011 (
#500000
0#
#505000
b100 "
b100 *
b100 %
1#
#506000
b101100 (
#510000
0#
#515000
b101 %
b101 "
b101 *
1#
#516000
b101101 (
#520000
0#
#525000
b110 "
b110 *
b110 %
1#
#526000
b101110 (
#530000
0#
#535000
b111 %
b111 "
b111 *
1#
#536000
b101111 (
#540000
0#
#545000
b1000 "
b1000 *
b1000 %
1#
#546000
b110000 (
#550000
0#
#555000
b1001 %
b1001 "
b1001 *
1#
#556000
b110001 (
#560000
0#
#565000
1!
b0 "
b0 *
1&
b0 %
1#
#566000
b110010 (
b101 )
#570000
0#
#575000
0&
b1 %
b1 "
b1 *
0!
1#
#576000
b110011 (
#580000
0#
#585000
b10 "
b10 *
b10 %
1#
#586000
b110100 (
#590000
0#
#595000
b11 %
b11 "
b11 *
1#
#596000
b110101 (
#600000
0#
#605000
b100 "
b100 *
b100 %
1#
#606000
b110110 (
#610000
0#
#615000
b101 %
b101 "
b101 *
1#
#616000
b110111 (
#620000
0#
#625000
b110 "
b110 *
b110 %
1#
#626000
b111000 (
#630000
0#
#635000
b111 %
b111 "
b111 *
1#
#636000
b111001 (
#640000
0#
#645000
b1000 "
b1000 *
b1000 %
1#
#646000
b111010 (
#650000
0#
#655000
b1001 %
b1001 "
b1001 *
1#
#656000
b111011 (
#660000
0#
#665000
1!
b0 "
b0 *
1&
b0 %
1#
#666000
b111100 (
b110 )
#670000
0#
#675000
0&
b1 %
b1 "
b1 *
0!
1#
#676000
b111101 (
#680000
0#
#685000
b10 "
b10 *
b10 %
1#
#686000
b111110 (
#690000
0#
#695000
b11 %
b11 "
b11 *
1#
#696000
b111111 (
#700000
0#
#705000
b100 "
b100 *
b100 %
1#
#706000
b1000000 (
#710000
0#
#715000
b101 %
b101 "
b101 *
1#
#716000
b1000001 (
#720000
0#
#725000
b110 "
b110 *
b110 %
1#
#726000
b1000010 (
#730000
0#
#735000
b111 %
b111 "
b111 *
1#
#736000
b1000011 (
#740000
0#
#745000
b1000 "
b1000 *
b1000 %
1#
#746000
b1000100 (
#750000
0#
#755000
b1001 %
b1001 "
b1001 *
1#
#756000
b1000101 (
#760000
0#
#765000
1!
b0 "
b0 *
1&
b0 %
1#
#766000
b1000110 (
b111 )
#770000
0#
#775000
0&
b1 %
b1 "
b1 *
0!
1#
#776000
b1000111 (
#780000
0#
#785000
b10 "
b10 *
b10 %
1#
#786000
b1001000 (
#790000
0#
#795000
b11 %
b11 "
b11 *
1#
#796000
b1001001 (
#800000
0#
#805000
b100 "
b100 *
b100 %
1#
#806000
b1001010 (
#810000
0#
#815000
b101 %
b101 "
b101 *
1#
#816000
b1001011 (
#820000
0#
#825000
b110 "
b110 *
b110 %
1#
#826000
b1001100 (
#830000
0#
#835000
b111 %
b111 "
b111 *
1#
#836000
b1001101 (
#840000
0#
#845000
b1000 "
b1000 *
b1000 %
1#
#846000
b1001110 (
#850000
0#
#855000
b1001 %
b1001 "
b1001 *
1#
#856000
b1001111 (
#860000
0#
#865000
1!
b0 "
b0 *
1&
b0 %
1#
#866000
b1010000 (
b1000 )
#870000
0#
#875000
0&
b1 %
b1 "
b1 *
0!
1#
#876000
b1010001 (
#880000
0#
#885000
b10 "
b10 *
b10 %
1#
#886000
b1010010 (
#890000
0#
#895000
b11 %
b11 "
b11 *
1#
#896000
b1010011 (
#900000
0#
#905000
b100 "
b100 *
b100 %
1#
#906000
b1010100 (
#910000
0#
#915000
b101 %
b101 "
b101 *
1#
#916000
b1010101 (
#920000
0#
#925000
b110 "
b110 *
b110 %
1#
#926000
b1010110 (
#930000
0#
#935000
b111 %
b111 "
b111 *
1#
#936000
b1010111 (
#940000
0#
#945000
b1000 "
b1000 *
b1000 %
1#
#946000
b1011000 (
#950000
0#
#955000
b1001 %
b1001 "
b1001 *
1#
#956000
b1011001 (
#960000
0#
#965000
1!
b0 "
b0 *
1&
b0 %
1#
#966000
b1011010 (
b1001 )
#970000
0#
#975000
0&
b1 %
b1 "
b1 *
0!
1#
#976000
b1011011 (
#980000
0#
#985000
b10 "
b10 *
b10 %
1#
#986000
b1011100 (
#990000
0#
#995000
b11 %
b11 "
b11 *
1#
#996000
b1011101 (
#1000000
0#
#1005000
b100 "
b100 *
b100 %
1#
#1006000
b1011110 (
#1010000
0#
#1015000
b101 %
b101 "
b101 *
1#
#1016000
b1011111 (
#1020000
0#
#1025000
b110 "
b110 *
b110 %
1#
#1026000
b1100000 (
#1030000
0#
#1035000
b111 %
b111 "
b111 *
1#
#1036000
b1100001 (
#1040000
0#
#1045000
b1000 "
b1000 *
b1000 %
1#
#1046000
b1100010 (
#1050000
0#
#1055000
b1001 %
b1001 "
b1001 *
1#
#1056000
b1100011 (
#1060000
0#
#1065000
1!
b0 "
b0 *
1&
b0 %
1#
#1066000
b1100100 (
b1010 )
