Ejercicios_Unidad_2/actividad_5/actividad_5.v
// contador
`timescale 1ns/1ps

module actividad_5 #(
    parameter WIDTHin = 8,
    parameter WIDTHout = 16,
    parameter A=8'sd5,
    parameter B=8'sd3
    )(
    input  wire        clk,
    input  wire        rst,
    input  wire signed [WIDTHin-1:0]  x_in,
    output wire signed  [WIDTHout-1:0]  y_out,
    input  wire        valid_in,
    output wire        ready_out,
    output wire         valid_out,
    input  wire        ready_in
);
reg signed [8:0]  stage1;
reg signed [16:0] stage2;
reg signed [16:0] stage3;

reg valid1;
reg valid2;
reg valid3;
assign ready_out = ready_in;

assign y_out     = stage3;
assign valid_out = valid3; 
always @(posedge clk) begin
    if (rst) begin
    stage1    <= 0;
    stage2    <= 0;
    stage3    <= 0;
    valid1    <= 0;
    valid2    <= 0;
    valid3    <= 0;
    end else if (ready_in) begin
        if (valid_in)
            stage1 <= x_in + A;
        valid1 <= valid_in;

        if (valid1)
            stage2 <= stage1 * B;
        valid2 <= valid1;

        if (valid2)
            stage3 <= stage2 >>> 4;
        valid3 <= valid2;
                
    end
end

endmodule

Ejercicios_Unidad_2/actividad_5/tb_actividad_5.v
`timescale 1ns/1ps
module tb_actividad_5;
reg clk;
reg rst;
reg signed [7:0] x_in;
reg valid_in;
reg ready_in;
wire signed [15:0] y_out;
wire valid_out;
wire ready_out;
actividad_5 dut(
    .clk(clk),
    .rst(rst),
    .x_in(x_in),
    .valid_in(valid_in),
    .ready_out(ready_out),
    .y_out(y_out),
    .valid_out(valid_out),
    .ready_in(ready_in)
);
initial
    clk = 0;
always #5 clk = ~clk;
reg signed [15:0] gold_pipe [0:2];
reg gold_valid [0:2];
integer i;
integer ciclos;
integer muestras;
always @(posedge clk) begin
    if (rst) begin
        gold_pipe[0]  <= 0;
        gold_pipe[1]  <= 0;
        gold_pipe[2]  <= 0;

        gold_valid[0] <= 0;
        gold_valid[1] <= 0;
        gold_valid[2] <= 0;
    end
    else if (ready_in) begin
        gold_pipe[0] <= ((x_in + 8'sd5) * 8'sd3) >>> 4;
        gold_valid[0] <= valid_in;

        gold_pipe[1] <= gold_pipe[0];
        gold_valid[1] <= gold_valid[0];

        gold_pipe[2] <= gold_pipe[1];
        gold_valid[2] <= gold_valid[1];
    end
end
always @(posedge clk) begin
    #1;
    if (valid_out != gold_valid[2]) begin
        $display("ERROR VALID tiempo=%0t", $time);
        $finish;
    end
    if (valid_out && (y_out !== gold_pipe[2])) begin
        $display("ERROR DATA tiempo=%0t  y=%0d esperado=%0d",
                 $time,
                 y_out,
                 gold_pipe[2]);
        $finish;
    end
end

initial begin

    $display("");
    $display("---------------------------------------------------------------------------------------------");
    $display(" tiempo | x_in | vin | stage1 v1 | stage2 v2 | stage3 v3 | y_out vout | ready");
    $display("---------------------------------------------------------------------------------------------");
end
always @(posedge clk) begin
    #1;
    $display("%6t | %4d |  %b  | %5d  %b | %5d  %b | %5d  %b | %5d   %b  |   %b",
             $time,
             x_in,
             valid_in,
             dut.stage1,
             dut.valid1,
             dut.stage2,
             dut.valid2,
             dut.stage3,
             dut.valid3,
             y_out,
             valid_out,
             ready_in);
end
always @(posedge clk) begin
    ciclos = ciclos + 1;
    if(valid_in && ready_out)
        muestras = muestras + 1;
end
initial begin
    $dumpfile("tb_actividad_5.vcd");
    $dumpvars(0,tb_actividad_5);
    rst      = 1;
    valid_in = 0;
    ready_in = 1;
    x_in     = 0;
    ciclos = 0;
    muestras = 0;
    @(posedge clk);
    #1;
    rst = 0;
    for(i=0;i<10;i=i+1) begin
        @(posedge clk);
        x_in = i;
        valid_in = 1;
    end
    valid_in = 0;
    @(posedge clk);
    ready_in = 0;
    $display("");
    $display("------------ STALL ACTIVADO ------------");
    repeat(4)
        @(posedge clk);
    ready_in = 1;
    $display("");
    $display("------------ STALL LIBERADO ------------");
    repeat(10)
        @(posedge clk);
    $display("");
    $display("SIMULACION TERMINADA");
    $display("Ciclos = %0d", ciclos);
    $display("Muestras procesadas = %0d", muestras);
    $display("Throughput observado = %f muestras/ciclo", muestras*1.0/ciclos);  
    $finish;
end

endmodule

Ejercicios_Unidad_2/actividad_5/tb_actividad_5.vcd
$date
	Wed Aug  5 21:06:28 2026
$end
$version
	Icarus Verilog
$end
$timescale
	1ps
$end
$scope module tb_actividad_5 $end
$var wire 16 ! y_out [15:0] $end
$var wire 1 " valid_out $end
$var wire 1 # ready_out $end
$var reg 1 $ clk $end
$var reg 1 % ready_in $end
$var reg 1 & rst $end
$var reg 1 ' valid_in $end
$var reg 8 ( x_in [7:0] $end
$var integer 32 ) ciclos [31:0] $end
$var integer 32 * i [31:0] $end
$var integer 32 + muestras [31:0] $end
$scope module dut $end
$var wire 1 $ clk $end
$var wire 1 % ready_in $end
$var wire 1 # ready_out $end
$var wire 1 & rst $end
$var wire 1 ' valid_in $end
$var wire 1 " valid_out $end
$var wire 8 , x_in [7:0] $end
$var wire 16 - y_out [15:0] $end
$var reg 9 . stage1 [8:0] $end
$var reg 17 / stage2 [16:0] $end
$var reg 17 0 stage3 [16:0] $end
$var reg 1 1 valid1 $end
$var reg 1 2 valid2 $end
$var reg 1 3 valid3 $end
$upscope $end
$upscope $end
$enddefinitions $end
#0
$dumpvars
x3
x2
x1
bx 0
bx /
bx .
bx -
b0 ,
b0 +
bx *
b0 )
b0 (
0'
1&
1%
0$
1#
x"
bx !
$end
#5000
b0 !
b0 -
0"
03
02
01
b0 0
b0 /
b0 .
b1 )
1$
#6000
b0 *
0&
#10000
0$
#15000
11
b101 .
b1 +
b10 )
b1 *
1'
1$
#20000
0$
#25000
12
b1111 /
b10 *
b1 (
b1 ,
b10 +
b11 )
1$
#30000
0$
#35000
1"
13
b111 .
b11 +
b100 )
b11 *
b10 (
b10 ,
1$
#40000
0$
#45000
b10101 /
b100 *
b11 (
b11 ,
b100 +
b101 )
1$
#50000
0$
#55000
b1 !
b1 -
b1 0
b1001 .
b101 +
b110 )
b101 *
b100 (
b100 ,
1$
#60000
0$
#65000
b11011 /
b110 *
b101 (
b101 ,
b110 +
b111 )
1$
#70000
0$
#75000
b1011 .
b111 +
b1000 )
b111 *
b110 (
b110 ,
1$
#80000
0$
#85000
b100001 /
b1000 *
b111 (
b111 ,
b1000 +
b1001 )
1$
#90000
0$
#95000
b10 !
b10 -
b10 0
b1101 .
b1001 +
b1010 )
b1001 *
b1000 (
b1000 ,
1$
#100000
0$
#105000
b100111 /
0'
b1010 *
b1001 (
b1001 ,
b1010 +
b1011 )
1$
#110000
0$
#115000
b1100 )
0#
0%
1$
#120000
0$
#125000
b1101 )
1$
#130000
0$
#135000
b1110 )
1$
#140000
0$
#145000
b1111 )
1$
#150000
0$
#155000
01
b10000 )
1#
1%
1$
#160000
0$
#165000
02
b10001 )
1$
#170000
0$
#175000
0"
03
b10010 )
1$
#180000
0$
#185000
b10011 )
1$
#190000
0$
#195000
b10100 )
1$
#200000
0$
#205000
b10101 )
1$
#210000
0$
#215000
b10110 )
1$
#220000
0$
#225000
b10111 )
1$
#230000
0$
#235000
b11000 )
1$
#240000
0$
#245000
b11001 )
1$
#250000
0$
#255000
b11010 )
1$
